CHANGES
LICENSE
MANIFEST.in
README
setup.cfg
setup.py
sphinxcontrib/__init__.py
sphinxcontrib/sdedit.py
sphinxcontrib_sdedit.egg-info/PKG-INFO
sphinxcontrib_sdedit.egg-info/SOURCES.txt
sphinxcontrib_sdedit.egg-info/dependency_links.txt
sphinxcontrib_sdedit.egg-info/namespace_packages.txt
sphinxcontrib_sdedit.egg-info/not-zip-safe
sphinxcontrib_sdedit.egg-info/requires.txt
sphinxcontrib_sdedit.egg-info/top_level.txt