Metadata-Version: 1.0
Name: sphinxcontrib-sdedit
Version: 0.3
Summary: Sphinx extension for drawing sequence diagrams
Home-page: http://bitbucket.org/birkenfeld/sphinx-contrib
Author: SHIBUKAWA Yoshiki
Author-email: yoshiki@shibu.jp
License: BSD
Download-URL: http://pypi.python.org/pypi/sphinxcontrib-sdedit
Platform: any
Classifier: Development Status :: 4 - Beta
Classifier: Environment :: Console
Classifier: Environment :: Web Environment
Classifier: Intended Audience :: Developers
Classifier: License :: OSI Approved :: BSD License
Classifier: Operating System :: OS Independent
Classifier: Programming Language :: Python
Classifier: Topic :: Documentation
Classifier: Topic :: Utilities
